[
  {
    "title": "Semifinal 1 | GS Caltex vs Hi-Pass | KOVO CUP 2025",
    "start": "2025-09-27T11:30:00+07:00",
    "src": "https://livecloud.pstatic.net/sports/lip2_kr/anmssgpu0002/4vreoi0ymkqj77oe7yeksuakzpghx2xg5tmg/playlist.m3u8?hdnts=st=1758946617~exp=1758979027~acl=*/4vreoi0ymkqj77oe7yeksuakzpghx2xg5tmg/*~hmac=81db3d852b7a382185769088fd2688595fa74e8f7142217aadd62be0ae05aa42",
    "poster": "assets/kebo cap.png"
  },
  {
    "title": "Semifinal 2 | IBK Altos vs Hyundai Hilstate | KOVO CUP 2025",
    "start": "2025-09-27T14:00:00+07:00",
    "src": "",
    "poster": "assets/kebo cap.png"
  }
]
